pip_missing_reqs/__init__.py
pip_missing_reqs/find_missing_reqs.py
pip_missing_reqs/test_find_missing_reqs.py
pip_missing_reqs-1.1.6.dist-info/DESCRIPTION.rst
pip_missing_reqs-1.1.6.dist-info/entry_points.txt
pip_missing_reqs-1.1.6.dist-info/METADATA
pip_missing_reqs-1.1.6.dist-info/metadata.json
pip_missing_reqs-1.1.6.dist-info/RECORD
pip_missing_reqs-1.1.6.dist-info/top_level.txt
pip_missing_reqs-1.1.6.dist-info/WHEEL
