Metadata-Version: 2.0
Name: pip-missing-reqs
Version: 1.1.6
Summary: Find packages that should be in requirements for a project
Home-page: https://github.com/r1chardj0n3s/pip-missing-reqs
Author: Richard Jonees
Author-email: r1chardj0n3s@gmail.com
License: MIT
Platform: UNKNOWN
Classifier: Development Status :: 4 - Beta
Classifier: Intended Audience :: Developers
Classifier: Topic :: Software Development :: Build Tools
Classifier: License :: OSI Approved :: MIT License
Classifier: Programming Language :: Python :: 2.7
Classifier: Programming Language :: Python :: 3
